Workbook
Name Slicer_State: #N/A

Sheet Clients
A1: Client_ID | B1: Client_Name | C1: Age | D1: Gender | E1: State | F1: City | G1: Employment_Type | H1: Annual_Income | I1: Has_Loan | J1: Loan_Amount | K1: Net_Worth | L1: Risk_Profile | M1: Investment_Type | N1: Client_Since | O1: Income Group | P1: Age Group | Q1: Annual Investments | R1: A Investment/Income %
A2: C1001 | B2: Pooja Reddy | C2: 41 | D2: Female | E2: Telangana | F2: Hyderabad | G2: Salaried | H2: 1240000 | I2: Yes | J2: 710000 | K2: 2666879 | L2: Moderate | M2: Mutual Funds | N2: 44440 | O2: =IF(H2<500000, "Low", IF(H2<=1500000, "Medium", "High")) -> Medium | P2: =IF(C2<18, "Children", IF(C2<=35, "Young Adults", IF(C2<=55, "Middle-Aged", "Seniors"))) -> Middle-Aged | Q2: =SUMIF(Monthly_Investments!$A$2:$A$18001,A2,Monthly_Investments!$F$2:$F$18001) -> 251985 | R2: =Q2/H2*100 -> 20.321371
A3: C1002 | B3: Ishita Singh | C3: 36 | D3: Female | E3: Punjab | F3: Ludhiana | G3: Self-Employed | H3: 480000 | I3: No | J3: 0 | K3: 1012851 | L3: Aggressive | M3: Mutual Funds | N3: 43647 | O3: =IF(H3<500000, "Low", IF(H3<=1500000, "Medium", "High")) -> Low | P3: =IF(C3<18, "Children", IF(C3<=35, "Young Adults", IF(C3<=55, "Middle-Aged", "Seniors"))) -> Middle-Aged | Q3: =SUMIF(Monthly_Investments!$A$2:$A$18001,A3,Monthly_Investments!$F$2:$F$18001) -> 41332 | R3: =Q3/H3*100 -> 8.6108333
A4: C1003 | B4: Aarav Sharma | C4: 60 | D4: Female | E4: Uttar Pradesh | F4: Noida | G4: Salaried | H4: 2080000 | I4: No | J4: 0 | K4: 9479856 | L4: Conservative | M4: Mutual Funds | N4: 44470 | O4: =IF(H4<500000, "Low", IF(H4<=1500000, "Medium", "High")) -> High | P4: =IF(C4<18, "Children", IF(C4<=35, "Young Adults", IF(C4<=55, "Middle-Aged", "Seniors"))) -> Seniors | Q4: =SUMIF(Monthly_Investments!$A$2:$A$18001,A4,Monthly_Investments!$F$2:$F$18001) -> 371722 | R4: =Q4/H4*100 -> 17.87125
A5: C1004 | B5: Sneha Singh | C5: 58 | D5: Female | E5: Gujarat | F5: Surat | G5: Salaried | H5: 1840000 | I5: No | J5: 0 | K5: 7050479 | L5: Conservative | M5: Gold | N5: 45597 | O5: =IF(H5<500000, "Low", IF(H5<=1500000, "Medium", "High")) -> High | P5: =IF(C5<18, "Children", IF(C5<=35, "Young Adults", IF(C5<=55, "Middle-Aged", "Seniors"))) -> Seniors | Q5: =SUMIF(Monthly_Investments!$A$2:$A$18001,A5,Monthly_Investments!$F$2:$F$18001) -> 376573 | R5: =Q5/H5*100 -> 20.465924
A6: C1005 | B6: Riya Roy | C6: 39 | D6: Male | E6: Karnataka | F6: Bengaluru | G6: Salaried | H6: 700000 | I6: Yes | J6: 270000 | K6: 3474476 | L6: Moderate | M6: Mutual Funds | N6: 43647 | O6: =IF(H6<500000, "Low", IF(H6<=1500000, "Medium", "High")) -> Medium | P6: =IF(C6<18, "Children", IF(C6<=35, "Young Adults", IF(C6<=55, "Middle-Aged", "Seniors"))) -> Middle-Aged | Q6: =SUMIF(Monthly_Investments!$A$2:$A$18001,A6,Monthly_Investments!$F$2:$F$18001) -> 127100 | R6: =Q6/H6*100 -> 18.157143
A7: C1006 | B7: Pooja Jain | C7: 52 | D7: Female | E7: Karnataka | F7: Bengaluru | G7: Salaried | H7: 530000 | I7: No | J7: 0 | K7: 2197980 | L7: Conservative | M7: Mutual Funds | N7: 44682 | O7: =IF(H7<500000, "Low", IF(H7<=1500000, "Medium", "High")) -> Medium | P7: =IF(C7<18, "Children", IF(C7<=35, "Young Adults", IF(C7<=55, "Middle-Aged", "Seniors"))) -> Middle-Aged | Q7: =SUMIF(Monthly_Investments!$A$2:$A$18001,A7,Monthly_Investments!$F$2:$F$18001) -> 50397 | R7: =Q7/H7*100 -> 9.5088679
A8: C1007 | B8: Vivaan Singh | C8: 31 | D8: Female | E8: Maharashtra | F8: Pune | G8: Salaried | H8: 280000 | I8: No | J8: 0 | K8: 484460 | L8: Moderate | M8: Fixed Deposits | N8: 45108 | O8: =IF(H8<500000, "Low", IF(H8<=1500000, "Medium", "High")) -> Low | P8: =IF(C8<18, "Children", IF(C8<=35, "Young Adults", IF(C8<=55, "Middle-Aged", "Seniors"))) -> Young Adults | Q8: =SUMIF(Monthly_Investments!$A$2:$A$18001,A8,Monthly_Investments!$F$2:$F$18001) -> 27068 | R8: =Q8/H8*100 -> 9.6671429
A9: C1008 | B9: Aditya Mishra | C9: 55 | D9: Female | E9: Kerala | F9: Kochi | G9: Salaried | H9: 430000 | I9: No | J9: 0 | K9: 648217 | L9: Conservative | M9: Equity | N9: 43647 | O9: =IF(H9<500000, "Low", IF(H9<=1500000, "Medium", "High")) -> Low | P9: =IF(C9<18, "Children", IF(C9<=35, "Young Adults", IF(C9<=55, "Middle-Aged", "Seniors"))) -> Middle-Aged | Q9: =SUMIF(Monthly_Investments!$A$2:$A$18001,A9,Monthly_Investments!$F$2:$F$18001) -> 91617 | R9: =Q9/H9*100 -> 21.306279
A10: C1009 | B10: Vivaan Malhotra | C10: 47 | D10: Female | E10: Gujarat | F10: Ahmedabad | G10: Self-Employed | H10: 1270000 | I10: Yes | J10: 260000 | K10: 4175491 | L10: Conservative | M10: Gold | N10: 45992 | O10: =IF(H10<500000, "Low", IF(H10<=1500000, "Medium", "High")) -> Medium | P10: =IF(C10<18, "Children", IF(C10<=35, "Young Adults", IF(C10<=55, "Middle-Aged", "Seniors"))) -> Middle-Aged | Q10: =SUMIF(Monthly_Investments!$A$2:$A$18001,A10,Monthly_Investments!$F$2:$F$18001) -> 305129 | R10: =Q10/H10*100 -> 24.025906
A11: C1010 | B11: Ankit Nair | C11: 36 | D11: Female | E11: Uttar Pradesh | F11: Noida | G11: Salaried | H11: 1010000 | I11: Yes | J11: 210000 | K11: 2292382 | L11: Moderate | M11: Gold | N11: 43983 | O11: =IF(H11<500000, "Low", IF(H11<=1500000, "Medium", "High")) -> Medium | P11: =IF(C11<18, "Children", IF(C11<=35, "Young Adults", IF(C11<=55, "Middle-Aged", "Seniors"))) -> Middle-Aged | Q11: =SUMIF(Monthly_Investments!$A$2:$A$18001,A11,Monthly_Investments!$F$2:$F$18001) -> 277797 | R11: =Q11/H11*100 -> 27.504653
A12: C1011 | B12: Meera Kumar | C12: 33 | D12: Male | E12: Maharashtra | F12: Mumbai | G12: Salaried | H12: 1120000 | I12: Yes | J12: 620000 | K12: 2156724 | L12: Moderate | M12: Gold | N12: 44743 | O12: =IF(H12<500000, "Low", IF(H12<=1500000, "Medium", "High")) -> Medium | P12: =IF(C12<18, "Children", IF(C12<=35, "Young Adults", IF(C12<=55, "Middle-Aged", "Seniors"))) -> Young Adults | Q12: =SUMIF(Monthly_Investments!$A$2:$A$18001,A12,Monthly_Investments!$F$2:$F$18001) -> 264415 | R12: =Q12/H12*100 -> 23.608482
A13: C1012 | B13: Sneha Nair | C13: 57 | D13: Female | E13: Punjab | F13: Chandigarh | G13: Salaried | H13: 310000 | I13: No | J13: 0 | K13: 1645066 | L13: Conservative | M13: Mutual Funds | N13: 45809 | O13: =IF(H13<500000, "Low", IF(H13<=1500000, "Medium", "High")) -> Low | P13: =IF(C13<18, "Children", IF(C13<=35, "Young Adults", IF(C13<=55, "Middle-Aged", "Seniors"))) -> Seniors | Q13: =SUMIF(Monthly_Investments!$A$2:$A$18001,A13,Monthly_Investments!$F$2:$F$18001) -> 84490 | R13: =Q13/H13*100 -> 27.254839
... A1501: C2500 | B1501: Ananya Das | C1501: 42 | D1501: Male | E1501: Kerala | F1501: Thiruvananthapuram | G1501: Self-Employed | H1501: 870000 | I1501: Yes | J1501: 440000 | K1501: 2031617 | L1501: Conservative | M1501: Mutual Funds | N1501: 45627 | O1501: =IF(H1501<500000, "Low", IF(H1501<=1500000, "Medium", "High")) -> Medium | P1501: =IF(C1501<18, "Children", IF(C1501<=35, "Young Adults", IF(C1501<=55, "Middle-Aged", "Seniors"))) -> Middle-Aged | Q1501: =SUMIF(Monthly_Investments!$A$2:$A$18001,A1501,Monthly_Investments!$F$2:$F$18001) -> 129340 | R1501: =Q1501/H1501*100 -> 14.866667

Sheet Monthly_Investments
A1: Client_ID | B1: Month | C1: State | D1: City | E1: Investment_Type | F1: Investment_Amount
A2: C1001 | B2: 2025-01 | C2: Telangana | D2: Hyderabad | E2: Mutual Funds | F2: 23538
A3: C1001 | B3: 2025-02 | C3: Telangana | D3: Hyderabad | E3: Mutual Funds | F3: 20616
A4: C1001 | B4: 2025-03 | C4: Telangana | D4: Hyderabad | E4: Mutual Funds | F4: 20819
A5: C1001 | B5: 2025-04 | C5: Telangana | D5: Hyderabad | E5: Mutual Funds | F5: 20595
A6: C1001 | B6: 2025-05 | C6: Telangana | D6: Hyderabad | E6: Mutual Funds | F6: 20427
A7: C1001 | B7: 2025-06 | C7: Telangana | D7: Hyderabad | E7: Mutual Funds | F7: 17925
A8: C1001 | B8: 2025-07 | C8: Telangana | D8: Hyderabad | E8: Mutual Funds | F8: 22983
A9: C1001 | B9: 2025-08 | C9: Telangana | D9: Hyderabad | E9: Mutual Funds | F9: 12990
A10: C1001 | B10: 2025-09 | C10: Telangana | D10: Hyderabad | E10: Mutual Funds | F10: 21964
A11: C1001 | B11: 2025-10 | C11: Telangana | D11: Hyderabad | E11: Mutual Funds | F11: 22452
A12: C1001 | B12: 2025-11 | C12: Telangana | D12: Hyderabad | E12: Mutual Funds | F12: 22874
A13: C1001 | B13: 2025-12 | C13: Telangana | D13: Hyderabad | E13: Mutual Funds | F13: 24802
... A18001: C2500 | B18001: 2025-12 | C18001: Kerala | D18001: Thiruvananthapuram | E18001: Mutual Funds | F18001: 14753

Sheet Pivot Tables
A1: Pivot Tables
A3: States | B3: Total Investments
A4: Delhi | B4: 109780000
A5: Gujarat | B5: 110940000
A6: Jharkhand | B6: 41220000
A7: Karnataka | B7: 175790000
A8: Kerala | B8: 89280000
A9: Madhya Pradesh | B9: 63970000
A10: Maharashtra | B10: 201520000
A11: Odisha | B11: 76640000
A12: Punjab | B12: 75750000
A13: Rajasthan | B13: 76280000
A14: Tamil Nadu | B14: 101070000
A15: Telangana | B15: 133050000
... A18: Grand Total | B18: 1469970000
A20: Income Groups | B20: AVG Investments
A21: High | B21: 2025450.5
A22: Low | B22: 388312.76
A23: Medium | B23: 894647.34
A24: Grand Total | B24: 979980
A26: Months | B26: Total Investment Amount
A27: 2025-01 | B27: 23605100
A28: 2025-02 | B28: 20142252
A29: 2025-03 | B29: 26071876
A30: 2025-04 | B30: 19855435
A31: 2025-05 | B31: 19603974
A32: 2025-06 | B32: 19241500
A33: 2025-07 | B33: 18539178
A34: 2025-08 | B34: 18786594
A35: 2025-09 | B35: 20261722
A36: 2025-10 | B36: 20920071
A37: 2025-11 | B37: 21832650
A38: 2025-12 | B38: 24676341
A39: Grand Total | B39: 253536693

Sheet Dashboard
A1: Total Clients | B1: Total Investment | C1: AVG Investment | D1: AVG Income
A2: 1500 | B2: =SUM(Clients!Q2:Q1501) -> 253536693 | C2: =AVERAGE(Clients!Q2:Q1501) -> 169024.46 | D2: =AVERAGE(Clients!H2:H1501) -> 979980
B4: Investment by States
A23: AVG Investment by Income Groups
B38: Monthly Investment Trend
